LICENSE
MANIFEST.in
README.rst
VERSION
setup.cfg
setup.py
doit_interface/__init__.py
doit_interface/actions.py
doit_interface/config.py
doit_interface/contexts.py
doit_interface/manager.py
doit_interface/reporters.py
doit_interface/util.py
doit_interface.egg-info/PKG-INFO
doit_interface.egg-info/SOURCES.txt
doit_interface.egg-info/dependency_links.txt
doit_interface.egg-info/entry_points.txt
doit_interface.egg-info/requires.txt
doit_interface.egg-info/top_level.txt
tests/__init__.py
tests/conftest.py
tests/test_actions.py
tests/test_contexts.py
tests/test_manager.py
tests/test_reporters.py
tests/test_util.py