Metadata-Version: 2.1
Name: doit-interface
Version: 0.1.8
Summary: A functional interface for creating doit tasks
Home-page: https://github.com/tillahoffmann/doit_interface
Provides-Extra: tests
Provides-Extra: docs
License-File: LICENSE
